cns/__init__.py
cns/cnsistent.py
cns/pipelines.py
cns/segment.py
cns/analyze/__init__.py
cns/analyze/aneuploidy.py
cns/analyze/breakage.py
cns/analyze/coverage.py
cns/analyze/distance.py
cns/analyze/plot.py
cns/process/__init__.py
cns/process/aggregation.py
cns/process/breakpoints.py
cns/process/clustering.py
cns/process/imputation.py
cns/process/normalize.py
cns/process/segments.py
cns/utils/__init__.py
cns/utils/anomaly.py
cns/utils/assemblies.py
cns/utils/canonization.py
cns/utils/conversions.py
cns/utils/cytobands.py
cns/utils/files.py
cns/utils/gaps.py
cns/utils/genomes.py
cns/utils/logging.py
cns/utils/misc.py
cns/utils/selection.py
cnsistent-0.9.0.dist-info/METADATA
cnsistent-0.9.0.dist-info/WHEEL
cnsistent-0.9.0.dist-info/entry_points.txt
cnsistent-0.9.0.dist-info/licenses/LICENSE.txt
cnsistent-0.9.0.dist-info/RECORD
