Metadata-Version: 2.4
Name: CNSistent
Version: 0.9.0
Summary: Tools for imputation, segmentation, analysis, and plotting of Copy Number Segments (CNS).
Author-email: Adam Streck <adam.streck@gmail.com>
Maintainer-email: Adam Streck <adam.streck@gmail.com>
License: MIT
License-File: LICENSE.txt
Keywords: CNS,bioinformatics,copy number segments,genomics
Requires-Python: >=3.9
Requires-Dist: matplotlib
Requires-Dist: numba
Requires-Dist: numpy
Requires-Dist: pandas>=2.2
Requires-Dist: scikit-learn
